speech_semaphore/__init__.py
speech_semaphore/sinthesis_with_pause.py
speech_semaphore-0.1.1.dist-info/METADATA
speech_semaphore-0.1.1.dist-info/WHEEL
speech_semaphore-0.1.1.dist-info/top_level.txt
speech_semaphore-0.1.1.dist-info/RECORD
