Metadata-Version: 2.1
Name: speech-semaphore
Version: 0.1.1
Summary: sinthesis speech with pauses
Home-page: UNKNOWN
Author: Roman Doronin
License: Apache License Version 2.0
Platform: UNKNOWN
Requires-Python: >=3.6
Requires-Dist: tinkoff-voicekit-client
